Workbook

Sheet Config
A1: CONFIG — All dashboard inputs live here
A2: ── LIVE MARKET DATA ── | C2: Pull via API on refresh
A3: NIFTY 50 Spot | B3: 22700 | C3: Source: Kite/DhanHQ ticker · format: #,##0
A4: NIFTY Day Change % | B4: 0.0038 | C4: Source: same · format: 0.0%
A5: NIFTY ATM IV % | B5: 0.142 | C5: ATM straddle mid ÷ BS reverse · format: 0.0%
A6: SENSEX Spot | B6: 79408 | C6: Source: Kite/DhanHQ BSE ticker · format: #,##0
A7: SENSEX Day Change % | B7: -0.0014 | C7: format: 0.0%
A8: SENSEX ATM IV % | B8: 0.138 | C8: format: 0.0%
A9: ── IV REGIME ──
A10: IVP (30-day rolling) | B10: 0.42 | C10: count(days IV < today) ÷ 30 · format: 0%
A11: ── EXPIRY & DTE ──
A12: Next expiry date | B12: 7-Apr-2026 | C12: NSE calendar · format: DD-MMM-YYYY
A13: Effective DTE | B13: 2 | C13: Calendar days adj. for weekends + NSE holidays
A14: ── FILTER THRESHOLDS ──
A15: IVP Floor | B15: 0.2 | C15: Skip if IVP below this · default 20%
A16: IVP Ceiling | B16: 0.8 | C16: Skip if IVP above this · default 80%
A17: Signal threshold | B17: 65 | C17: Min score to generate SELL signal · default 65
A18: Exclude Fridays | B18: YES | C18: YES/NO
A19: Lookback months | B19: 12 | C19: For monthly % calculation
A20: ── INSTRUMENT ──
A21: Active instrument | B21: NIFTY 50 | C21: NIFTY 50 or SENSEX
A22: NIFTY lot size | B22: 65 | C22: NSE standard lot
A23: SENSEX lot size | B23: 10 | C23: BSE standard lot
A24: Capital base (₹) | B24: 500000 | C24: For return% and DD% calculations

Sheet Tab1_Backtest
A1: SHORT STRANGLE BACKTESTING DASHBOARD — Tab 1: Backtest Results
A2: DATA SOURCES & GROUND RULES | Bhavcopy (NSE EOD, free) → default | DhanHQ / Kite API → live feed | Lot size: NIFTY=65, SENSEX=10 | Capital base: ₹5,00,000 | Brokerage: ₹80/trade flat | STT: 0.05% on exit premium | IVP window: 30-day rolling | Friday entries excluded | Holiday-adjusted DTE
A3: NIFTY 50 Spot | B3: =Config!B3 -> 22700 | C3: NIFTY Chg% | D3: =Config!B4 -> 0.0038 | E3: NIFTY IV% | F3: =Config!B5 -> 0.142 | G3: SENSEX Spot | H3: =Config!B7 -> -0.0014 | I3: SENSEX Chg% | J3: =Config!B8 -> 0.138 | K3: SENSEX IV% | L3: =Config!B9 -> 0
A4: Instrument | B4: Entry time | C4: Exit time | D4: Lookback (months) | E4: IVP Floor (%) | F4: IVP Ceiling (%) | G4: Excl. Fridays? | H4: Signal threshold | I4: Period (1D/1H/5M)
A5: NIFTY 50 | B5: T-2 closing | C5: T closing | D5: 12 | E5: 20 | F5: 80 | G5: YES | H5: 65 | I5: 1D
A6: Strike offset | B6: Gross P&L (₹) | C6: Costs (₹) | D6: Net P&L (₹) | E6: Net P&L monthly % | F6: Return on ₹5L (%) | G6: Max DD (₹) | H6: Max DD monthly % | I6: Vega (₹ per 1% IV) | J6: Theta (₹/day) | K6: Cushion ratio (Theta÷|Vega|) | L6: Signal score (/100)
A7: NIFTY 50 — Capital: ₹1,20,000 per lot | Lot size: 65
A8: ±2.5% | B8: 16840 | C8: 1980 | D8: =B8-C8 -> 14860 | E8: =IFERROR(D8/(Config!B24*Config!B19),0) -> 0.0024766667 | F8: =IFERROR(D8/Config!B24,0) -> 0.02972 | G8: -5613 | H8: =IFERROR(G8/(Config!B24*Config!B19),0) -> -0.0009355 | I8: -340 | J8: 620 | K8: =J8/ABS(I8) -> 1.8235294 | L8: =MIN(100,ROUND(J8/ABS(I8)*30+50,0)) -> 100
A9: ±3.0% | B9: 20480 | C9: 2060 | D9: =B9-C9 -> 18420 | E9: =IFERROR(D9/(Config!B24*Config!B19),0) -> 0.00307 | F9: =IFERROR(D9/Config!B24,0) -> 0.03684 | G9: -6826 | H9: =IFERROR(G9/(Config!B24*Config!B19),0) -> -0.0011376667 | I9: -290 | J9: 510 | K9: =J9/ABS(I9) -> 1.7586207 | L9: =MIN(100,ROUND(J9/ABS(I9)*30+50,0)) -> 100
A10: ±3.5% ★ Best | B10: 24960 | C10: 2200 | D10: =B10-C10 -> 22760 | E10: =IFERROR(D10/(Config!B24*Config!B19),0) -> 0.0037933333 | F10: =IFERROR(D10/Config!B24,0) -> 0.04552 | G10: -8320 | H10: =IFERROR(G10/(Config!B24*Config!B19),0) -> -0.0013866667 | I10: -220 | J10: 440 | K10: =J10/ABS(I10) -> 2 | L10: =MIN(100,ROUND(J10/ABS(I10)*30+50,0)) -> 100
A11: ±4.0% | B11: 18700 | C11: 2110 | D11: =B11-C11 -> 16590 | E11: =IFERROR(D11/(Config!B24*Config!B19),0) -> 0.002765 | F11: =IFERROR(D11/Config!B24,0) -> 0.03318 | G11: -6233 | H11: =IFERROR(G11/(Config!B24*Config!B19),0) -> -0.0010388333 | I11: -160 | J11: 370 | K11: =J11/ABS(I11) -> 2.3125 | L11: =MIN(100,ROUND(J11/ABS(I11)*30+50,0)) -> 100
A12: ±4.5% | B12: 11200 | C12: 2010 | D12: =B12-C12 -> 9190 | E12: =IFERROR(D12/(Config!B24*Config!B19),0) -> 0.0015316667 | F12: =IFERROR(D12/Config!B24,0) -> 0.01838 | G12: -3733 | H12: =IFERROR(G12/(Config!B24*Config!B19),0) -> -0.00062216667 | I12: -110 | J12: 290 | K12: =J12/ABS(I12) -> 2.6363636 | L12: =MIN(100,ROUND(J12/ABS(I12)*30+50,0)) -> 100
A13: SENSEX — Capital: ₹1,10,000 per lot | Lot size: 10
A14: ±2.5% | B14: 9200 | C14: 1050 | D14: =B14-C14 -> 8150 | E14: =IFERROR(D14/(Config!B24*Config!B19),0) -> 0.0013583333 | F14: =IFERROR(D14/Config!B24,0) -> 0.0163 | G14: -3066 | H14: =IFERROR(G14/(Config!B24*Config!B19),0) -> -0.000511 | I14: -180 | J14: 340 | K14: =J14/ABS(I14) -> 1.8888889 | L14: =MIN(100,ROUND(J14/ABS(I14)*30+50,0)) -> 100
A15: ±3.0% | B15: 11600 | C15: 1100 | D15: =B15-C15 -> 10500 | E15: =IFERROR(D15/(Config!B24*Config!B19),0) -> 0.00175 | F15: =IFERROR(D15/Config!B24,0) -> 0.021 | G15: -3866 | H15: =IFERROR(G15/(Config!B24*Config!B19),0) -> -0.00064433333 | I15: -150 | J15: 280 | K15: =J15/ABS(I15) -> 1.8666667 | L15: =MIN(100,ROUND(J15/ABS(I15)*30+50,0)) -> 100
A16: ±3.5% ★ Best | B16: 13800 | C16: 1160 | D16: =B16-C16 -> 12640 | E16: =IFERROR(D16/(Config!B24*Config!B19),0) -> 0.0021066667 | F16: =IFERROR(D16/Config!B24,0) -> 0.02528 | G16: -4600 | H16: =IFERROR(G16/(Config!B24*Config!B19),0) -> -0.00076666667 | I16: -110 | J16: 230 | K16: =J16/ABS(I16) -> 2.0909091 | L16: =MIN(100,ROUND(J16/ABS(I16)*30+50,0)) -> 100
A17: ±4.0% | B17: 10400 | C17: 1120 | D17: =B17-C17 -> 9280 | E17: =IFERROR(D17/(Config!B24*Config!B19),0) -> 0.0015466667 | F17: =IFERROR(D17/Config!B24,0) -> 0.01856 | G17: -3466 | H17: =IFERROR(G17/(Config!B24*Config!B19),0) -> -0.00057766667 | I17: -90 | J17: 200 | K17: =J17/ABS(I17) -> 2.2222222 | L17: =MIN(100,ROUND(J17/ABS(I17)*30+50,0)) -> 100
A18: ±4.5% | B18: 6800 | C18: 1080 | D18: =B18-C18 -> 5720 | E18: =IFERROR(D18/(Config!B24*Config!B19),0) -> 0.00095333333 | F18: =IFERROR(D18/Config!B24,0) -> 0.01144 | G18: -2266 | H18: =IFERROR(G18/(Config!B24*Config!B19),0) -> -0.00037766667 | I18: -60 | J18: 160 | K18: =J18/ABS(I18) -> 2.6666667 | L18: =MIN(100,ROUND(J18/ABS(I18)*30+50,0)) -> 100
A20: GLOSSARY & DISPLAY RULES
A21: Net P&L monthly % | B21: Net P&L ÷ (₹5,00,000 × lookback months). Shows annualised pace of return on capital deployed.
A22: Max DD monthly % | B22: Largest peak-to-trough loss ÷ (₹5,00,000 × months). Negative = capital at risk per month.
A23: Vega (₹ per 1% IV) | B23: How much your P&L changes for every 1% rise in Implied Volatility. NEGATIVE because you are SHORT vol. Example: Vega = −₹220 → IV spikes +5% → you lose ₹1,100 on that leg.
A24: Theta (₹/day) | B24: Daily time-decay income collected. POSITIVE because you are SHORT options. Example: Theta = +₹440 → you earn ₹440 for every calendar day the position is held, all else equal.
A25: Cushion ratio | B25: Theta ÷ |Vega|. Answers: 'How many IV points must spike in ONE day to wipe today's Theta?' ≥2.0x = safe zone (green). 1–2x = watch zone (amber). <1x = danger (red).
A26: Signal score | B26: Composite 0–100. 60% weight on BS strike probability (N·d2) + 40% on IVP premium quality. ≥65 = SELL. 50–64 = MONITOR. <50 = AVOID.
A27: IVP floor/ceiling | B27: IVP <20 → skip (vol too low, Vega expansion risk). IVP >80 → skip (Gamma spike risk). 20–80 = trade zone.
A28: Holiday DTE adjust | B28: If next expiry falls after a public holiday, DTE is reduced accordingly. Example: Apr 7 expiry with Apr 5-6 holidays = effective DTE of 2, not 4. All Theta and probability calculations use adjusted DTE.
A29: Display format rules | B29: ₹ values: whole numbers, no decimals. % values: one decimal (e.g. 1.6%). Ratios: one decimal + x (e.g. 2.3x). Scores: integer out of 100.
A30: Blue cells | B30: User inputs — change these to update scenarios.
A31: Black cells | B31: Excel formulas — do not overwrite.
A32: Green cells | B32: Cross-sheet links pulling from Config sheet.

Sheet Tab2_LiveSignal
A1: LIVE SIGNAL SHEET — Tab 2: Next Expiry | Immediate next weekly / monthly contract
A2: DATA SOURCE: Live feed via DhanHQ or Kite API (fallback: NSE Bhavcopy EOD T-1 close) | Time snapshots: 10 AM / 11 AM / 12 PM / 1 PM / 2 PM / 3 PM | DTE: Calendar days adjusted for NSE holidays — no trading on Sat/Sun/holidays | Strike probability: Black-Scholes N(d2) using live ATM IV | Extreme loss scenario: 0.5% beyond outer strike (1 day before expiry max)
A3: NIFTY 50 Spot | B3: =Config!B3 -> 22700 | C3: NIFTY IV% | D3: =Config!B5 -> 0.142 | E3: SENSEX Spot | F3: =Config!B7 -> -0.0014 | G3: Snapshot time → use dropdown in Config
A4: Next expiry | B4: =Config!B12 -> 7-Apr-2026 | C4: DTE (adj.) | D4: =Config!B13 -> 2 | E4: IVP (30d) | F4: =Config!B6 -> 79408 | G4: Regime / signal threshold
A5: PUT LEG → | B5: −4.5% 21,680 | C5: −4.0% 21,792 | D5: −3.5% 21,905 | E5: −3.0% 22,019 | F5: −2.5% 22,133
A6: Premium (₹) | B6: 8 | C6: 14 | D6: 22 | E6: 38 | F6: 64 | G6: Live ATM mid-price from option chain. Source: Kite/DhanHQ API or NSE EOD
A7: Profit/lot (₹) | B7: =IFERROR(B6*65,0) -> 520 | C7: =IFERROR(C6*65,0) -> 910 | D7: =IFERROR(D6*65,0) -> 1430 | E7: =IFERROR(E6*65,0) -> 2470 | F7: =IFERROR(F6*65,0) -> 4160 | G7: Premium × lot size (NIFTY=65, SENSEX=10). No decimals.
A8: Capital req. (₹) | B8: 28400 | C8: 29100 | D8: 30200 | E8: 31800 | F8: 33600 | G8: SPAN + Exposure margin. Source: broker margin calculator API
A9: Return/lot (%) | B9: =IFERROR(B7/B8,0) -> 0.018309859 | C9: =IFERROR(C7/C8,0) -> 0.031271478 | D9: =IFERROR(D7/D8,0) -> 0.047350993 | E9: =IFERROR(E7/E8,0) -> 0.077672956 | F9: =IFERROR(F7/F8,0) -> 0.12380952 | G9: Profit per lot ÷ Capital required. Format: 0.0%
A10: Prob – N(d2) % | B10: 94 | C10: 91 | D10: 86 | E10: 78 | F10: 66 | G10: BS probability spot stays above put strike at expiry. Uses live IV + holiday-adj DTE
A11: Cushion ratio | B11: 2.8 | C11: 2.3 | D11: 1.7 | E11: 1.2 | F11: 0.8 | G11: Theta ÷ |Vega|. Green ≥2x · Amber 1–2x · Red <1x
A12: Signal score | B12: 71 | C12: 66 | D12: 59 | E12: 52 | F12: 41 | G12: 60% × Prob + 40% × IVP_quality_score. ≥65=SELL · 50-64=MONITOR · <50=AVOID
A13: Action | B13: SELL | C13: SELL | D13: MONITOR | E13: MONITOR | F13: AVOID | G13: Auto-generated from signal score vs threshold in Config!B16
A14: Extreme loss 0.5% (₹) | G14: Loss if spot moves 0.5% beyond outer strike on last day. = (Strike − Spot) × lot × contracts
A16: CALL LEG → | B16: +2.5% 23,268 | C16: +3.0% 23,381 | D16: +3.5% 23,494 | E16: +4.0% 23,608 | F16: +6.6% 24,200* | G16: * Your example from worked case
A17: Premium (₹) | B17: 58 | C17: 34 | D17: 19 | E17: 10 | F17: 15 | G17: Live ATM mid-price from option chain. Source: Kite/DhanHQ API or NSE EOD
A18: Profit/lot (₹) | B18: =IFERROR(B17*65,0) -> 3770 | C18: =IFERROR(C17*65,0) -> 2210 | D18: =IFERROR(D17*65,0) -> 1235 | E18: =IFERROR(E17*65,0) -> 650 | F18: =IFERROR(F17*65,0) -> 975 | G18: Premium × lot size (NIFTY=65, SENSEX=10). No decimals.
A19: Capital req. (₹) | B19: 34200 | C19: 32800 | D19: 31400 | E19: 29900 | F19: 28600 | G19: SPAN + Exposure margin. Source: broker margin calculator API
A20: Return/lot (%) | B20: =IFERROR(B18/B19,0) -> 0.11023392 | C20: =IFERROR(C18/C19,0) -> 0.067378049 | D20: =IFERROR(D18/D19,0) -> 0.03933121 | E20: =IFERROR(E18/E19,0) -> 0.02173913 | F20: =IFERROR(F18/F19,0) -> 0.034090909 | G20: Profit per lot ÷ Capital required. Format: 0.0%
A21: Prob – N(d2) % | B21: 72 | C21: 83 | D21: 91 | E21: 96 | F21: 99 | G21: BS probability spot stays above put strike at expiry. Uses live IV + holiday-adj DTE
A22: Cushion ratio | B22: 0.9 | C22: 1.4 | D22: 2.1 | E22: 2.9 | F22: 3.1 | G22: Theta ÷ |Vega|. Green ≥2x · Amber 1–2x · Red <1x
A23: Signal score | B23: 48 | C23: 58 | D23: 67 | E23: 76 | F23: 84 | G23: 60% × Prob + 40% × IVP_quality_score. ≥65=SELL · 50-64=MONITOR · <50=AVOID
A24: Action | B24: AVOID | C24: MONITOR | D24: SELL | E24: SELL | F24: SELL★ | G24: Auto-generated from signal score vs threshold in Config!B16
A25: Extreme loss 0.5% (₹) | G25: Loss if spot moves 0.5% beyond outer strike on last day. = (Strike − Spot) × lot × contracts
A27: GLOSSARY — LIVE SIGNAL SHEET
A28: Prob N(d2) | B28: Black-Scholes N(d2): probability the option expires worthless (out-of-the-money). Inputs: Spot, Strike, IV (annualised), Risk-free rate (~6.5% India), holiday-adjusted DTE. 94% on a put means: market implies 94% chance spot stays above that strike at expiry.
A29: Cushion ratio | B29: Theta ÷ |Vega|. Number of IV percentage-points that must spike in ONE day to wipe your entire daily Theta income. Example: Theta=+₹440, Vega=−₹220 → ratio=2.0x → IV needs to rise 2 full points (e.g. 14%→16%) in a single day to cancel out your decay income. ≥2x green · 1–2x amber · <1x red.
A30: Signal score | B30: Composite 0–100. Formula: (N(d2) probability × 0.60) + (IVP quality score × 0.40). IVP quality score = IVP × 1.25 capped at 100 (peaks at IVP=80). Threshold for SELL is set in Config sheet (default 65). Raise to 75 for conservative weeks.
A31: Extreme loss 0.5% | B31: Scenario: spot moves 0.5% BEYOND the outer strike on the last trading day before expiry. Why 0.5%? You enter at fag-end of theta decay on near-expiry contracts — extreme moves beyond this are tail events. Formula: (Strike − Spot_extreme) × lot_size × no_of_contracts. Shown as negative ₹ loss. Use this to size position so loss < 5% of capital.
A32: Holiday DTE | B32: Effective DTE = Calendar days to expiry MINUS weekend days MINUS NSE public holidays. Example: Trade on Apr 3 (Thursday), expiry Apr 7 (Monday). Apr 5 (Sat), Apr 6 (Sun) = 0 trading. Effective DTE = 2 (Thu close → Mon open only). This compresses Theta AND tightens N(d2) — probability rises sharply, making far-OTM sells safer near expiry.
A33: Display rules | B33: All ₹ values: integers only, Indian comma format. Percentages: one decimal place. Ratios: one decimal + x. Scores: integer. Negative P&L: shown in (brackets).

Sheet Tab3_IV_History
A1: IV HISTORY — Tab 3: 30-Period Chart | Period selector: 1D / 1H / 5M
A2: DATA SOURCE: NSE Bhavcopy for 1D (EOD IV from ATM mid-price). DhanHQ Historical API or Kite Instruments for 1H and 5M intraday. Pull last 30 periods of the selected timeframe. NIFTY IV = ATM straddle mid ÷ spot × √(365/DTE) × 100 (annualised). SENSEX IV = same formula applied to BSE option chain.
A3: 1D | B3: =Config!B3 -> 22700 | C3: =Config!B5 -> 0.142 | D3: =Config!B7 -> -0.0014 | E3: =Config!B9 -> 0 | F3: =Config!B6 -> 79408 | G3: =IF(Config!B6<Config!B14,"LOW – skip",IF(Config!B6>Config!B15,"HIGH – skip","ALLOW")) -> HIGH – skip
A4: Period # | B4: Date / Time | C4: NIFTY ATM IV% | D4: NIFTY IVP rank | E4: SENSEX ATM IV% | F4: SENSEX IVP rank | G4: Notes
A5: 30 | B5: ← pull from data source (period 30) | C5: ← API / Bhavcopy | D5: ← API / Bhavcopy | E5: ← API / Bhavcopy | F5: ← API / Bhavcopy | G5: Auto from IVP rank
A6: 29 | B6: ← pull from data source (period 29) | C6: ← API / Bhavcopy | D6: ← API / Bhavcopy | E6: ← API / Bhavcopy | F6: ← API / Bhavcopy | G6: Auto from IVP rank
A7: 28 | B7: ← pull from data source (period 28) | C7: ← API / Bhavcopy | D7: ← API / Bhavcopy | E7: ← API / Bhavcopy | F7: ← API / Bhavcopy | G7: Auto from IVP rank
A8: 27 | B8: ← pull from data source (period 27) | C8: ← API / Bhavcopy | D8: ← API / Bhavcopy | E8: ← API / Bhavcopy | F8: ← API / Bhavcopy | G8: Auto from IVP rank
A9: 26 | B9: ← pull from data source (period 26) | C9: ← API / Bhavcopy | D9: ← API / Bhavcopy | E9: ← API / Bhavcopy | F9: ← API / Bhavcopy | G9: Auto from IVP rank
A10: 25 | B10: ← pull from data source (period 25) | C10: ← API / Bhavcopy | D10: ← API / Bhavcopy | E10: ← API / Bhavcopy | F10: ← API / Bhavcopy | G10: Auto from IVP rank
A11: 24 | B11: ← pull from data source (period 24) | C11: ← API / Bhavcopy | D11: ← API / Bhavcopy | E11: ← API / Bhavcopy | F11: ← API / Bhavcopy | G11: Auto from IVP rank
A12: 23 | B12: ← pull from data source (period 23) | C12: ← API / Bhavcopy | D12: ← API / Bhavcopy | E12: ← API / Bhavcopy | F12: ← API / Bhavcopy | G12: Auto from IVP rank
A13: 22 | B13: ← pull from data source (period 22) | C13: ← API / Bhavcopy | D13: ← API / Bhavcopy | E13: ← API / Bhavcopy | F13: ← API / Bhavcopy | G13: Auto from IVP rank
A14: 21 | B14: ← pull from data source (period 21) | C14: ← API / Bhavcopy | D14: ← API / Bhavcopy | E14: ← API / Bhavcopy | F14: ← API / Bhavcopy | G14: Auto from IVP rank
A15: 20 | B15: ← pull from data source (period 20) | C15: ← API / Bhavcopy | D15: ← API / Bhavcopy | E15: ← API / Bhavcopy | F15: ← API / Bhavcopy | G15: Auto from IVP rank
A16: 19 | B16: ← pull from data source (period 19) | C16: ← API / Bhavcopy | D16: ← API / Bhavcopy | E16: ← API / Bhavcopy | F16: ← API / Bhavcopy | G16: Auto from IVP rank
... A34: 1 | B34: ← pull from data source (period 1) | C34: ← API / Bhavcopy | D34: ← API / Bhavcopy | E34: ← API / Bhavcopy | F34: ← API / Bhavcopy | G34: Auto from IVP rank
A36: INSERT CHART HERE: Select B5:C34, Insert → Line Chart → 'NIFTY ATM IV (30 periods)'. Add second series E5:E34 for SENSEX IV. Add horizontal reference lines at IVP Floor (Config!B14) and Ceiling (Config!B15). Label axes: X = Period, Y = IV%. Title = 'Implied Volatility — Last 30 Periods'.
A38: GLOSSARY — IV HISTORY SHEET
A39: ATM IV% | B39: Implied Volatility extracted from At-The-Money option mid-price using Black-Scholes reverse. Represents market's consensus forecast of future volatility. Higher = market fears larger moves.
A40: IVP rank | B40: IV Percentile over last 30 periods of selected timeframe. Formula: count(periods where IV < today's IV) ÷ 30. 0% = IV at historic low. 100% = IV at historic high. Trade zone: 20%–80%.
A41: 1D period | B41: Each row = one trading day's closing ATM IV. Source: NSE Bhavcopy. Free, T+1 available by 6 PM.
A42: 1H period | B42: Each row = one hourly candle IV snapshot. Source: DhanHQ Historical API or Kite Instruments endpoint. Requires API key. Best for intraday signal refinement.
A43: 5M period | B43: Each row = one 5-minute candle. Source: same as 1H. Use only for final-hour entry timing. High noise — cross-check with 1D IVP before acting.
A44: How to read | B44: Rising IV + low IVP → vol expanding from base → cautious. Falling IV + high IVP → vol compressing from peak → ideal selling environment. Flat IV in mid-IVP → stable → standard signal logic applies.
